hqm/__init__.py
hqm/circuits/__init__.py
hqm/circuits/amplitudeencoding.py
hqm/circuits/angleencoding.py
hqm/circuits/circuit.py
hqm/circuits/customcircuits.py
hqm/circuits/flexiblecircuit.py
hqm/classification/__init__.py
hqm/classification/hcnn.py
hqm/classification/hmlp.py
hqm/encoding/__init__.py
hqm/encoding/autoencoders.py
hqm/layers/__init__.py
hqm/layers/basiclayer.py
hqm/layers/quanvolution.py
hqm/layers/recurrent.py
hqm/noise/__init__.py
hqm/noise/gaussianlike.py
hqm/noise/randomcircuit.py
hqm/regression/__init__.py
hqm/regression/hmlp.py
hqm/utils/__init__.py
hqm/utils/aiinterface.py
hqm/utils/printer.py
hqm/utils/sizes.py
hqm-0.0.19.dist-info/licenses/LICENSE
hqm-0.0.19.dist-info/METADATA
hqm-0.0.19.dist-info/WHEEL
hqm-0.0.19.dist-info/top_level.txt
hqm-0.0.19.dist-info/RECORD
