Metadata-Version: 2.4
Name: hqm
Version: 0.0.19
Summary: Hybrid Quantum Models - HQM
Home-page: https://github.com/alessandrosebastianelli/hybrid_quantum_models.git
Author: Alessandro Sebastianelli
Author-email: Alessandro Sebastianelli <alessandro.sebastianelli1995@gmail.com>
License: Copyright (c) 2023-2023 Alessandro Sebastianelli
Project-URL: Homepage, https://github.com/alessandrosebastianelli/hybrid_quantum_models
Project-URL: Bug Tracker, https://github.com/alessandrosebastianelli/hybrid_quantum_models/issues
Project-URL: How to contribute, https://github.com/alessandrosebastianelli/hybrid_quantum_models/issues/1
Classifier: Programming Language :: Python :: 3
Classifier: License :: OSI Approved :: MIT License
Classifier: Operating System :: OS Independent
Requires-Python: >=3.9.17
License-File: LICENSE
Requires-Dist: numpy==1.23.5
Requires-Dist: pennylane==0.28.0
Dynamic: author
Dynamic: home-page
Dynamic: license-file
